odoo/addons/account_payment_register_keep_amount/README.rst
odoo/addons/account_payment_register_keep_amount/__init__.py
odoo/addons/account_payment_register_keep_amount/__manifest__.py
odoo/addons/account_payment_register_keep_amount/i18n/account_payment_register_keep_amount.pot
odoo/addons/account_payment_register_keep_amount/i18n/es.po
odoo/addons/account_payment_register_keep_amount/readme/CONFIGURE.rst
odoo/addons/account_payment_register_keep_amount/readme/CONTRIBUTORS.rst
odoo/addons/account_payment_register_keep_amount/readme/DESCRIPTION.rst
odoo/addons/account_payment_register_keep_amount/static/description/icon.png
odoo/addons/account_payment_register_keep_amount/static/description/index.html
odoo/addons/account_payment_register_keep_amount/tests/__init__.py
odoo/addons/account_payment_register_keep_amount/tests/test_account_payment_register.py
odoo/addons/account_payment_register_keep_amount/wizards/__init__.py
odoo/addons/account_payment_register_keep_amount/wizards/account_payment_register.py
odoo/addons/account_payment_register_keep_amount/wizards/account_payment_register_views.xml
odoo14_addon_account_payment_register_keep_amount-14.0.1.0.1.dev4.dist-info/METADATA
odoo14_addon_account_payment_register_keep_amount-14.0.1.0.1.dev4.dist-info/WHEEL
odoo14_addon_account_payment_register_keep_amount-14.0.1.0.1.dev4.dist-info/top_level.txt
odoo14_addon_account_payment_register_keep_amount-14.0.1.0.1.dev4.dist-info/RECORD
